README.md
setup.py
lm_dataloader/__init__.py
lm_dataloader/cmd_line.py
lm_dataloader/encode.py
lm_dataloader/indexed_dataset.py
lm_dataloader/lm_dataset.py
lm_dataloader/samplers.py
lm_dataloader/utils.py
lm_dataloader.egg-info/PKG-INFO
lm_dataloader.egg-info/SOURCES.txt
lm_dataloader.egg-info/dependency_links.txt
lm_dataloader.egg-info/entry_points.txt
lm_dataloader.egg-info/requires.txt
lm_dataloader.egg-info/top_level.txt
test/__init__.py
test/tests.py