Metadata-Version: 2.1
Name: lm-dataloader
Version: 0.0.2
Summary: Dataloader tools for language modelling
Home-page: https://github.com/sdtblck/lm_dataloader
Author: Sid Black
Author-email: sdtblck@gmail.com
License: MIT
Platform: UNKNOWN
Classifier: License :: OSI Approved :: MIT License
Classifier: Programming Language :: Python :: 3.6
Classifier: Programming Language :: Python :: 3.7
Classifier: Programming Language :: Python :: 3.8
Classifier: Programming Language :: Python :: 3.9
Classifier: Programming Language :: Python :: 3.10
